pyawsopstoolkit_models/__init__.py
pyawsopstoolkit_models/__validation__.py
pyawsopstoolkit_models/ec2/__init__.py
pyawsopstoolkit_models/ec2/security_group.py
pyawsopstoolkit_models/iam/__init__.py
pyawsopstoolkit_models/iam/permissions_boundary.py
pyawsopstoolkit_models/iam/role.py
pyawsopstoolkit_models/iam/user.py
pyawsopstoolkit_models-0.1.1.dist-info/LICENSE
pyawsopstoolkit_models-0.1.1.dist-info/METADATA
pyawsopstoolkit_models-0.1.1.dist-info/WHEEL
pyawsopstoolkit_models-0.1.1.dist-info/top_level.txt
pyawsopstoolkit_models-0.1.1.dist-info/RECORD
