Metadata-Version: 2.1
Name: pyawsopstoolkit-models
Version: 0.1.1
Summary: This package provides a comprehensive collection of data model classes specifically designed for various AWS Ops
Home-page: https://github.com/coldsofttech/pyawsopstoolkit-models.git
Author: coldsofttech
License: MIT
Keywords: aws,toolkit,operations,tools,development,python,models,utilities,amazon-web-services
Classifier: Development Status :: 4 - Beta
Classifier: Intended Audience :: Developers
Classifier: Topic :: Software Development :: Libraries
Classifier: Topic :: Software Development :: Libraries :: Python Modules
Classifier: License :: OSI Approved :: MIT License
Classifier: Programming Language :: Python :: 3.10
Classifier: Programming Language :: Python :: 3.11
Classifier: Programming Language :: Python :: 3.12
License-File: LICENSE
Requires-Dist: pyawsopstoolkit==0.1.19
Requires-Dist: pyawsopstoolkit-validators==0.1.0
